utils/__init__.py
utils/sam_utils.py
utils/utils.py
utils/yolo_utils.py
SAMY-1.0.0.dist-info/LICENSE
SAMY-1.0.0.dist-info/METADATA
SAMY-1.0.0.dist-info/WHEEL
SAMY-1.0.0.dist-info/top_level.txt
SAMY-1.0.0.dist-info/RECORD
